PDUUSSDConverter
