Metadata-Version: 1.1
Name: PDUUSSDConverter
Version: 0.0.2.post1
Summary: A utility to convert between pdu, gsm codes,     ussd and string formats
Home-page: https://github.com/saviour123/PDU-USSDConverter.git
Author: Saviour Gidi
Author-email: profsaviour@gmail.com
License: MIT
Keywords: PDU USSD GSM HEX
Platform: UNKNOWN
Classifier: Development Status :: 3 - Alpha
Classifier: Programming Language :: Python :: 3
Classifier: Topic :: Utilities
Classifier: License :: OSI Approved :: MIT License
